LICENSE.txt
MANIFEST.in
README.md
requirements.txt
setup.cfg
setup.py
bufferapp/__init__.py
bufferapp/api.py
bufferapp/response.py
bufferapp/test.py
bufferapp.egg-info/PKG-INFO
bufferapp.egg-info/SOURCES.txt
bufferapp.egg-info/dependency_links.txt
bufferapp.egg-info/requires.txt
bufferapp.egg-info/top_level.txt
bufferapp/managers/__init__.py
bufferapp/managers/profiles.py
bufferapp/managers/updates.py
bufferapp/models/__init__.py
bufferapp/models/link.py
bufferapp/models/profile.py
bufferapp/models/update.py
bufferapp/models/user.py
bufferapp/tests/__init__.py
bufferapp/tests/test_api.py
bufferapp/tests/test_link.py
bufferapp/tests/test_profile.py
bufferapp/tests/test_profiles_manager.py
bufferapp/tests/test_response.py
bufferapp/tests/test_update.py
bufferapp/tests/test_updates_manager.py
bufferapp/tests/test_user.py