Metadata-Version: 1.1
Name: bufferapp
Version: 0.2.0
Summary: Python library for Buffer App
Home-page: https://github.com/mardix/bufferapp
Author: Mardix, Vlad Temian
Author-email: mardix@pylot.io, vladtemian@gmail.com
License: UNKNOWN
Platform: any
Classifier: Programming Language :: Python :: 2.7
